<?xml version="1.0" encoding="UTF-8"?>
<krpano version="1.19"
        onstart="startup"
        logkey="false"
        bgcolor="#ffffff"
        projectfloorplanurl="%FIRSTXML%/floorplan/_108310721085.png"
        projecttitleid="project_title"
        projectdescriptionid="project_description">


  <security cors="">
    <!--
    <crossdomainxml url="http://RESSOURCES_URL/crossdomain.xml" />
    -->
    <allowdomain domain="*" />
  </security>

  <krpano tour_firststartactiondone="false" />
  <events name="startbehavioursevents" onxmlcomplete="startbehavioursxmlcompleteaction();" keep="true"/>

  <!-- generated by Panotour Pro V2.5.1 64bits : 17-05-2019 03-30-08 -->
  <!-- Plugins and Spot Styles -->
  <include url="%FIRSTXML%/Tour_skin.xml"/>
  <!-- Core actions -->
  <include url="%FIRSTXML%/Tour_core.xml"/>
  <!-- Tour Messages -->
  <include url="%FIRSTXML%/Tour_messages_ru.xml"/>

  <action name="startup">

    if (s !== null, if (startscene === null, set(startscene, get(s));); );
    if (startscene === null,
      set(startscene, pano100);
    );
    mainloadsceneStartup(get(startscene));
    if (h !== null,
      if (v !== null,
        if (f !== null,
          lookat(get(h), get(v), get(f));
         ,
          lookat(get(h), get(v));
        );
      ,
        if (f !== null,
          lookat(get(h), get(view.vlookat), get(f));
         ,
          lookat(get(h), get(view.vlookat));
        );
      );
    ,
      if (v !== null,
        if (f !== null,
          lookat(get(view.hlookat), get(v), get(f));
         ,
          lookat(get(view.hlookat), get(v));
        );
      ,
        if (f !== null,
          lookat(get(view.hlookat), get(view.vlookat), get(f));
        );
      );
    );
  </action>

  <!-- 1 Groups -->
  <panoramagroup name="panogroup40"
                 mainscene="pano100"
                 color="808080"
                 alpha="1"
                 thumburl="%FIRSTXML%/gxwu5119_100/thumbnail.jpg"
                 floorplanurl=""
                 titleid="panogroup40_title"
                 descriptionid=""/>

  <!-- Group Group Tour : 10 panoramas -->
  

<!-- **** @PanoName="Улица" @PanoFile="C:/Users/Сергей/Desktop/Фото Панорам/GXWU5119.JPG" **** -->
<!-- **** Width="0px" Height="0px" **** -->
<scene name="pano100"
       latitude="0"
       longitude="0"
       heading="170.0000000000002"
       group="panogroup40"
       thumburl="%FIRSTXML%/gxwu5119_100/thumbnail.jpg"
       backgroundsound=""
       backgroundsoundloops="0"
       haslocalsounds="false"
       haspolygons="true"
       titleid="pano100_title"
       descriptionid="pano100_description"
       multires="true"
       planar="false"
       full360="false"
       video="false"
       seen="false">

    <autorotate horizon="0.000000" tofov="63.542800" waittime="1" speed="5"/>


    <panoview h="-173.000000" v="0.000000" fov="63.542800" hmin="-180" hmax="180" vmin="-31.7714" vmax="31.7714" fovmax="90" />

    <view fisheye="0"
          limitview="range"
          hlookatmin="-180"
          hlookatmax="180"
          vlookatmin="-31.7714"
          vlookatmax="31.7714"
          maxpixelzoom="1.0"
          fovtype="VFOV"
          fovmax="90"
          fov="63.542800"
          hlookat="-173.000000"
          vlookat="0.000000"/>

    <preview url="%FIRSTXML%/gxwu5119_100/preview.jpg" type="CUBESTRIP" striporder="FRBLUD" />


        <image type="SPHERE" hfov="360" vfov="63.5428" voffset="0" multires="true" baseindex="0" tilesize="512" devices="flash.and.desktop">
          <level tiledimagewidth="9501" tiledimageheight="1674">
            <sphere url="gxwu5119_100/1/%v_%u.jpg"/>
          </level>
          <level tiledimagewidth="4750" tiledimageheight="837">
            <sphere url="gxwu5119_100/0/%v_%u.jpg"/>
          </level>
        </image>
  
  <image type="CUBE" devices="desktop.and.html5">
    <front url="gxwu5119_100/html5/0.jpg"/>
    <right url="gxwu5119_100/html5/1.jpg"/>
    <back  url="gxwu5119_100/html5/2.jpg"/>
    <left  url="gxwu5119_100/html5/3.jpg"/>
    <up    url="gxwu5119_100/html5/4.jpg"/>
    <down  url="gxwu5119_100/html5/5.jpg"/>
  </image>
  
      <image type="CUBE" devices="tablet">
        <front url="gxwu5119_100/tablet/0.jpg"/>
        <right url="gxwu5119_100/tablet/1.jpg"/>
        <back  url="gxwu5119_100/tablet/2.jpg"/>
        <left  url="gxwu5119_100/tablet/3.jpg"/>
        <up    url="gxwu5119_100/tablet/4.jpg"/>
        <down  url="gxwu5119_100/tablet/5.jpg"/>
      </image>
      <image type="CUBE" devices="mobile">
        <front url="gxwu5119_100/mobile/0.jpg"/>
        <right url="gxwu5119_100/mobile/1.jpg"/>
        <back  url="gxwu5119_100/mobile/2.jpg"/>
        <left  url="gxwu5119_100/mobile/3.jpg"/>
        <up    url="gxwu5119_100/mobile/4.jpg"/>
        <down  url="gxwu5119_100/mobile/5.jpg"/>
      </image>


  <!-- **** 1 Polygonal Spots **** -->


  <hotspot name="spotpolygon107"
           tag="polygon"
           style="PolygonDefaultPolygonSpotStyle"
           descriptionid=""
           onclick="onclickspotpolygon107"
           tooltip="spotpolygon107_tooltip"
           >
    <point ath="-174.417372" atv="1.374304" />
    <point ath="-174.736368" atv="-10.913857" />
    <point ath="-164.368620" atv="-11.237226" />
    <point ath="-164.368620" atv="1.050934" />
  </hotspot>
  <hotspot name="spotpolygon107" devices="flash" zorder="1"/>
  <hotspot name="spotpolygon107" devices="html5" zorder="3" zorder2="1"/>


  <action name="onclickspotpolygon107">
  
        mainloadscene(pano39);lookat(get(panoview.h), get(panoview.v), get(panoview.fov));


  </action>


  <action name="hidepanopolygonalspots">
    set(hotspot[spotpolygon107].visible, false);
  </action>
  <action name="showpanopolygonalspots">
    set(hotspot[spotpolygon107].visible, true);
  </action>
  <action name="removepanopolygonalspots">
    removehotspot(spotpolygon107);
  </action>

  <!-- **** 1 Picture Spots **** -->


  <hotspot name="spotpicture173"
           tag="picture"
           style="RectPictureFlyingPictureSpot"
           descriptionid=""
           url="%FIRSTXML%/spots/_1088107710841103_108810721073108610901099.png"
           ath="-177.359248"
           atv="-5.811734"
           width="26"
           height="28"
           rx="-30.883785419736281"
           ry="2.8711763445028953"
           rz="-0.11609326821458296"
           enabled="true"
           capture="false"
           onclick="onclickspotpicture173"

           flying="0.0"
           zorder="2"
           zorder_backup="2"
           />
  <action name="onclickspotpicture173">
    if(flying == 1.0, spotflybackspotpicture173(), spotflyoutspotpicture173() );
  

  </action>


  <action name="spotflyoutspotpicture173">
    ifnot (hotspot[spotpicture173].flying == 1.0,
      events.dispatch(onremovedisplayedobject);
      tween(hotspot[spotpicture173].rx, 0);
      tween(hotspot[spotpicture173].ry, 0);
      tween(hotspot[spotpicture173].rz, 0);
      tween(hotspot[spotpicture173].width , 1018);
      tween(hotspot[spotpicture173].height, 899);
      copy(hotspot[spotpicture173].zorder_backup, hotspot[spotpicture173].zorder);
      set(hotspot[spotpicture173].zorder, 10);
      set(hotspot[spotpicture173].zorder2, 1);
      setzorder2onstandardspots(0);

      tween(hotspot[spotpicture173].flying, 1.0);
    );
  </action>
  <action name="spotflybackspotpicture173">
    ifnot (hotspot[spotpicture173].flying == 0.0,
      tween(hotspot[spotpicture173].rx, -30.883785419736281);
      tween(hotspot[spotpicture173].ry, 2.8711763445028953);
      tween(hotspot[spotpicture173].rz, -0.11609326821458296);
      tween(hotspot[spotpicture173].width , 26);
      tween(hotspot[spotpicture173].height, 28);
      set(hotspot[spotpicture173].zorder, get(hotspot[spotpicture173].zorder_backup));
      set(hotspot[spotpicture173].zorder2, 0.0);
      setzorder2onstandardspots(1);

      tween(hotspot[spotpicture173].flying, 0.0);
    );
  </action>
  <events name="eventsspotpicture173" onremovedisplayedobject="spotflybackspotpicture173"/>

  <action name="hidepanopicturespots">
    set(hotspot[spotpicture173].visible, false);
  </action>
  <action name="showpanopicturespots">
    set(hotspot[spotpicture173].visible, true);
  </action>

  <!-- **** 2 Point Spots **** -->



  <hotspot name="spotpoint223"
           ath="-169.344936" atv="-4.995480"
           style="IconLoadpanorama"
           tag="point"
           descriptionid=""
           onclick="onclickspotpoint223"
           tooltip="spotpoint223_tooltip"
           />
  <hotspot name="spotpoint223" devices="flash" zorder="3"/>
  <hotspot name="spotpoint223" devices="html5" zorder="3" zorder2="1"/>
  <action name="onclickspotpoint223">
  
        mainloadscene(pano39);lookat(get(panoview.h), get(panoview.v), get(panoview.fov));


  </action>





  <hotspot name="spotpoint300"
           ath="-177.334272" atv="-5.797199"
           style="IconDisplayanimage"
           tag="point"
           descriptionid=""
           onclick="onclickspotpoint300"
           />
  <hotspot name="spotpoint300" devices="flash" zorder="3"/>
  <hotspot name="spotpoint300" devices="html5" zorder="3" zorder2="1"/>
  <action name="onclickspotpoint300">
  
displayImage(%FIRSTXML%/spots/time_work.png
             ,center,0,0
             ,700
             ,700

             ,false
             ,false
             ,false
             ,false
             ,000000
             ,0);

  </action>



  <action name="hidepanopointspots">
    set(hotspot[spotpoint223].visible, false);
    set(hotspot[spotpoint300].visible, false);
  </action>
  <action name="showpanopointspots">
    set(hotspot[spotpoint223].visible, true);
    set(hotspot[spotpoint300].visible, true);
  </action>
  <events name="pano100stopanimatedspots" onremovepano="stopspotanimation(spotpoint223);stopspotanimation(spotpoint300);" />


  <action name="showpanospotsaction">
    resumeTourSoundsActions(true,false,false,false,true);
    if (tour_displayspots,
    showpanopointspots();
    showpanopicturespots();
    showpanopolygonalspots();
    );
  </action>
  <action name="hidepanospotsaction">
    pauseTourSoundsActions(true,false,false,false,true);
    hidepanopointspots();
    hidepanopicturespots();
    hidepanopolygonalspots();
  </action>


  <action name="setzorder2onstandardspots">
    if (device.html5,
      ifnot (device.desktop,

        tween(hotspot[spotpolygon107].zorder2, %1);


        tween(hotspot[spotpoint223].zorder2, %1);

        tween(hotspot[spotpoint300].zorder2, %1);

      );
    );
  </action>


</scene>



<!-- **** @PanoName="Главный холл" @PanoFile="D:/Panorama/Photopano/photopano1.JPG" **** -->
<!-- **** Width="0px" Height="0px" **** -->
<scene name="pano39"
       heading="179.59999999999971"
       group="panogroup40"
       thumburl="%FIRSTXML%/_7ba84952_38cf_409e_8_39/thumbnail.jpg"
       backgroundsound=""
       backgroundsoundloops="0"
       haslocalsounds="false"
       haspolygons="true"
       titleid="pano39_title"
       descriptionid="pano39_description"
       multires="true"
       planar="false"
       full360="false"
       video="false"
       seen="false">

    <autorotate horizon="0.000000" tofov="65.021000" waittime="1" speed="5"/>


    <panoview h="177.000000" v="0.000000" fov="65.021000" hmin="-180" hmax="180" vmin="-32.5105" vmax="32.5105" fovmax="100" />

    <view fisheye="0"
          limitview="range"
          hlookatmin="-180"
          hlookatmax="180"
          vlookatmin="-32.5105"
          vlookatmax="32.5105"
          maxpixelzoom=""
          fovmin="65.021000000000001"
          fovtype="VFOV"
          fovmax="100"
          fov="65.021000"
          hlookat="177.000000"
          vlookat="0.000000"/>

    <preview url="%FIRSTXML%/_7ba84952_38cf_409e_8_39/preview.jpg" type="CUBESTRIP" striporder="FRBLUD" />


        <image type="SPHERE" hfov="360" vfov="65.021000000000001" voffset="0" multires="true" baseindex="0" tilesize="512" devices="flash.and.desktop">
          <level tiledimagewidth="9739" tiledimageheight="1754">
            <sphere url="_7ba84952_38cf_409e_8_39/1/%v_%u.jpg"/>
          </level>
          <level tiledimagewidth="4869" tiledimageheight="877">
            <sphere url="_7ba84952_38cf_409e_8_39/0/%v_%u.jpg"/>
          </level>
        </image>
  
  <image type="CUBE" devices="desktop.and.html5">
    <front url="_7ba84952_38cf_409e_8_39/html5/0.jpg"/>
    <right url="_7ba84952_38cf_409e_8_39/html5/1.jpg"/>
    <back  url="_7ba84952_38cf_409e_8_39/html5/2.jpg"/>
    <left  url="_7ba84952_38cf_409e_8_39/html5/3.jpg"/>
    <up    url="_7ba84952_38cf_409e_8_39/html5/4.jpg"/>
    <down  url="_7ba84952_38cf_409e_8_39/html5/5.jpg"/>
  </image>
  
      <image type="CUBE" devices="tablet">
        <front url="_7ba84952_38cf_409e_8_39/tablet/0.jpg"/>
        <right url="_7ba84952_38cf_409e_8_39/tablet/1.jpg"/>
        <back  url="_7ba84952_38cf_409e_8_39/tablet/2.jpg"/>
        <left  url="_7ba84952_38cf_409e_8_39/tablet/3.jpg"/>
        <up    url="_7ba84952_38cf_409e_8_39/tablet/4.jpg"/>
        <down  url="_7ba84952_38cf_409e_8_39/tablet/5.jpg"/>
      </image>
      <image type="CUBE" devices="mobile">
        <front url="_7ba84952_38cf_409e_8_39/mobile/0.jpg"/>
        <right url="_7ba84952_38cf_409e_8_39/mobile/1.jpg"/>
        <back  url="_7ba84952_38cf_409e_8_39/mobile/2.jpg"/>
        <left  url="_7ba84952_38cf_409e_8_39/mobile/3.jpg"/>
        <up    url="_7ba84952_38cf_409e_8_39/mobile/4.jpg"/>
        <down  url="_7ba84952_38cf_409e_8_39/mobile/5.jpg"/>
      </image>


  <!-- **** 2 Polygonal Spots **** -->


  <hotspot name="spotpolygon111"
           tag="polygon"
           style="PolygonDefaultPolygonSpotStyle"
           descriptionid=""
           onclick="onclickspotpolygon111"
           tooltip="spotpolygon111_tooltip"
           >
    <point ath="171.987480" atv="-8.296420" />
    <point ath="171.798840" atv="6.463543" />
    <point ath="175.286880" atv="5.112926" />
    <point ath="175.380840" atv="-8.103502" />
  </hotspot>
  <hotspot name="spotpolygon111" devices="flash" zorder="1"/>
  <hotspot name="spotpolygon111" devices="html5" zorder="3" zorder2="1"/>


  <action name="onclickspotpolygon111">
  
        mainloadscene(pano38);lookat(get(panoview.h), get(panoview.v), get(panoview.fov));


  </action>



  <hotspot name="spotpolygon113"
           tag="polygon"
           style="PolygonDefaultPolygonSpotStyle"
           descriptionid=""
           onclick="onclickspotpolygon113"
           tooltip="spotpolygon113_tooltip"
           >
    <point ath="-1.674720" atv="15.767593" />
    <point ath="-1.834200" atv="-10.728465" />
    <point ath="20.017800" atv="-10.240807" />
    <point ath="19.698840" atv="16.255250" />
  </hotspot>
  <hotspot name="spotpolygon113" devices="flash" zorder="1"/>
  <hotspot name="spotpolygon113" devices="html5" zorder="3" zorder2="1"/>


  <action name="onclickspotpolygon113">
  
        mainloadscene(pano100);lookat(get(panoview.h), get(panoview.v), get(panoview.fov));


  </action>


  <action name="hidepanopolygonalspots">
    set(hotspot[spotpolygon111].visible, false);
    set(hotspot[spotpolygon113].visible, false);
  </action>
  <action name="showpanopolygonalspots">
    set(hotspot[spotpolygon111].visible, true);
    set(hotspot[spotpolygon113].visible, true);
  </action>
  <action name="removepanopolygonalspots">
    removehotspot(spotpolygon111);
    removehotspot(spotpolygon113);
  </action>

  <!-- **** 3 Point Spots **** -->



  <hotspot name="spotpoint301"
           ath="5.767930" atv="1.689765"
           style="IconLoadpanorama"
           tag="point"
           descriptionid=""
           onclick="onclickspotpoint301"
           tooltip="spotpoint301_tooltip"
           />
  <hotspot name="spotpoint301" devices="flash" zorder="3"/>
  <hotspot name="spotpoint301" devices="html5" zorder="3" zorder2="1"/>
  <action name="onclickspotpoint301">
  
        mainloadscene(pano100);lookat(get(panoview.h), get(panoview.v), get(panoview.fov));


  </action>





  <hotspot name="spotpoint303"
           ath="173.237400" atv="-1.419408"
           style="IconLoadpanorama"
           tag="point"
           descriptionid=""
           onclick="onclickspotpoint303"
           tooltip="spotpoint303_tooltip"
           />
  <hotspot name="spotpoint303" devices="flash" zorder="3"/>
  <hotspot name="spotpoint303" devices="html5" zorder="3" zorder2="1"/>
  <action name="onclickspotpoint303">
  
        mainloadscene(pano38);lookat(get(panoview.h), get(panoview.v), get(panoview.fov));


  </action>





  <hotspot name="spotpoint306"
           ath="91.082883" atv="6.476546"
           style="IconDisplayanimage1"
           tag="point"
           descriptionid="spotpoint306_description"
           onclick="onclickspotpoint306"
           />
  <hotspot name="spotpoint306" devices="flash" zorder="3"/>
  <hotspot name="spotpoint306" devices="html5" zorder="3" zorder2="1"/>
  <action name="onclickspotpoint306">
  
displayImage(%FIRSTXML%/spots/info1.png
             ,center,0,0
             ,'',''
             ,false
             ,false
             ,false
             ,false
             ,000000
             ,0);

  </action>



  <action name="hidepanopointspots">
    set(hotspot[spotpoint301].visible, false);
    set(hotspot[spotpoint303].visible, false);
    set(hotspot[spotpoint306].visible, false);
  </action>
  <action name="showpanopointspots">
    set(hotspot[spotpoint301].visible, true);
    set(hotspot[spotpoint303].visible, true);
    set(hotspot[spotpoint306].visible, true);
  </action>
  <events name="pano39stopanimatedspots" onremovepano="stopspotanimation(spotpoint301);stopspotanimation(spotpoint303);stopspotanimation(spotpoint306);" />


  <action name="showpanospotsaction">
    resumeTourSoundsActions(true,false,false,false,true);
    if (tour_displayspots,
    showpanopointspots();
    showpanopolygonalspots();
    );
  </action>
  <action name="hidepanospotsaction">
    pauseTourSoundsActions(true,false,false,false,true);
    hidepanopointspots();
    hidepanopolygonalspots();
  </action>


  <action name="setzorder2onstandardspots">
    if (device.html5,
      ifnot (device.desktop,

        tween(hotspot[spotpolygon111].zorder2, %1);

        tween(hotspot[spotpolygon113].zorder2, %1);


        tween(hotspot[spotpoint301].zorder2, %1);

        tween(hotspot[spotpoint303].zorder2, %1);

        tween(hotspot[spotpoint306].zorder2, %1);

      );
    );
  </action>


</scene>



<!-- **** @PanoName="Выставка Рюриковичи" @PanoFile="D:/Panorama/Photopano/photopano2.JPG" **** -->
<!-- **** Width="0px" Height="0px" **** -->
<scene name="pano38"
       heading="-48.599999999999973"
       group="panogroup40"
       thumburl="%FIRSTXML%/_67341826_38f8_49ca_9_38/thumbnail.jpg"
       backgroundsound=""
       backgroundsoundloops="0"
       haslocalsounds="false"
       haspolygons="true"
       titleid="pano38_title"
       descriptionid="pano38_description"
       multires="true"
       planar="false"
       full360="false"
       video="false"
       seen="false">

    <autorotate horizon="0.000000" tofov="61.324400" waittime="1" speed="5"/>


    <panoview h="-134.910000" v="0.000000" fov="61.324400" hmin="-180" hmax="180" vmin="-30.662199999999999" vmax="30.662199999999999" fovmax="90" />

    <view fisheye="0"
          limitview="range"
          hlookatmin="-180"
          hlookatmax="180"
          vlookatmin="-30.662199999999999"
          vlookatmax="30.662199999999999"
          maxpixelzoom="1.0"
          fovtype="VFOV"
          fovmax="90"
          fov="61.324400"
          hlookat="-134.910000"
          vlookat="0.000000"/>

    <preview url="%FIRSTXML%/_67341826_38f8_49ca_9_38/preview.jpg" type="CUBESTRIP" striporder="FRBLUD" />


        <image type="SPHERE" hfov="360" vfov="61.324399999999997" voffset="0" multires="true" baseindex="0" tilesize="512" devices="flash.and.desktop">
          <level tiledimagewidth="10103" tiledimageheight="1716">
            <sphere url="_67341826_38f8_49ca_9_38/1/%v_%u.jpg"/>
          </level>
          <level tiledimagewidth="5051" tiledimageheight="858">
            <sphere url="_67341826_38f8_49ca_9_38/0/%v_%u.jpg"/>
          </level>
        </image>
  
  <image type="CUBE" devices="desktop.and.html5">
    <front url="_67341826_38f8_49ca_9_38/html5/0.jpg"/>
    <right url="_67341826_38f8_49ca_9_38/html5/1.jpg"/>
    <back  url="_67341826_38f8_49ca_9_38/html5/2.jpg"/>
    <left  url="_67341826_38f8_49ca_9_38/html5/3.jpg"/>
    <up    url="_67341826_38f8_49ca_9_38/html5/4.jpg"/>
    <down  url="_67341826_38f8_49ca_9_38/html5/5.jpg"/>
  </image>
  
      <image type="CUBE" devices="tablet">
        <front url="_67341826_38f8_49ca_9_38/tablet/0.jpg"/>
        <right url="_67341826_38f8_49ca_9_38/tablet/1.jpg"/>
        <back  url="_67341826_38f8_49ca_9_38/tablet/2.jpg"/>
        <left  url="_67341826_38f8_49ca_9_38/tablet/3.jpg"/>
        <up    url="_67341826_38f8_49ca_9_38/tablet/4.jpg"/>
        <down  url="_67341826_38f8_49ca_9_38/tablet/5.jpg"/>
      </image>
      <image type="CUBE" devices="mobile">
        <front url="_67341826_38f8_49ca_9_38/mobile/0.jpg"/>
        <right url="_67341826_38f8_49ca_9_38/mobile/1.jpg"/>
        <back  url="_67341826_38f8_49ca_9_38/mobile/2.jpg"/>
        <left  url="_67341826_38f8_49ca_9_38/mobile/3.jpg"/>
        <up    url="_67341826_38f8_49ca_9_38/mobile/4.jpg"/>
        <down  url="_67341826_38f8_49ca_9_38/mobile/5.jpg"/>
      </image>


  <!-- **** 2 Polygonal Spots **** -->


  <hotspot name="spotpolygon114"
           tag="polygon"
           style="PolygonDefaultPolygonSpotStyle"
           descriptionid=""
           onclick="onclickspotpolygon114"
           tooltip="spotpolygon114_tooltip"
           >
    <point ath="101.917800" atv="24.861218" />
    <point ath="137.671200" atv="26.104325" />
    <point ath="137.671200" atv="-24.861243" />
    <point ath="132.739560" atv="-29.833493" />
    <point ath="100.274040" atv="-29.419136" />
  </hotspot>
  <hotspot name="spotpolygon114" devices="flash" zorder="1"/>
  <hotspot name="spotpolygon114" devices="html5" zorder="3" zorder2="1"/>


  <action name="onclickspotpolygon114">
  
        mainloadscene(pano39);lookat(get(panoview.h), get(panoview.v), get(panoview.fov));


  </action>



  <hotspot name="spotpolygon117"
           tag="polygon"
           style="PolygonDefaultPolygonSpotStyle"
           descriptionid=""
           onclick="onclickspotpolygon117"
           tooltip="spotpolygon117_tooltip"
           >
    <point ath="20.939040" atv="16.494853" />
    <point ath="32.603400" atv="8.905223" />
    <point ath="60.418440" atv="7.286075" />
    <point ath="51.844320" atv="20.745063" />
  </hotspot>
  <hotspot name="spotpolygon117" devices="flash" zorder="1"/>
  <hotspot name="spotpolygon117" devices="html5" zorder="3" zorder2="1"/>


  <action name="onclickspotpolygon117">
  
        mainloadscene(pano118);lookat(get(panoview.h), get(panoview.v), get(panoview.fov));


  </action>


  <action name="hidepanopolygonalspots">
    set(hotspot[spotpolygon114].visible, false);
    set(hotspot[spotpolygon117].visible, false);
  </action>
  <action name="showpanopolygonalspots">
    set(hotspot[spotpolygon114].visible, true);
    set(hotspot[spotpolygon117].visible, true);
  </action>
  <action name="removepanopolygonalspots">
    removehotspot(spotpolygon114);
    removehotspot(spotpolygon117);
  </action>

  <!-- **** 1 Picture Spots **** -->


  <hotspot name="spotpicture137"
           tag="picture"
           style="RectPictureFlyingPictureSpot"
           descriptionid=""
           url="%FIRSTXML%/spots/untitled-4.png"
           ath="-92.284591"
           atv="12.898325"
           width="45"
           height="99"
           rx="-52.91726261155361"
           ry="9.7840847346110458"
           rz="9.2316018589588111"
           enabled="true"
           capture="false"
           onclick="onclickspotpicture137"

           flying="0.0"
           zorder="2"
           zorder_backup="2"
           />
  <action name="onclickspotpicture137">
    if(flying == 1.0, spotflybackspotpicture137(), spotflyoutspotpicture137() );
  

  </action>


  <action name="spotflyoutspotpicture137">
    ifnot (hotspot[spotpicture137].flying == 1.0,
      events.dispatch(onremovedisplayedobject);
      tween(hotspot[spotpicture137].rx, 0);
      tween(hotspot[spotpicture137].ry, 0);
      tween(hotspot[spotpicture137].rz, 0);
      tween(hotspot[spotpicture137].width , 500);
      tween(hotspot[spotpicture137].height, 800);
      copy(hotspot[spotpicture137].zorder_backup, hotspot[spotpicture137].zorder);
      set(hotspot[spotpicture137].zorder, 10);
      set(hotspot[spotpicture137].zorder2, 1);
      setzorder2onstandardspots(0);

      tween(hotspot[spotpicture137].flying, 1.0);
    );
  </action>
  <action name="spotflybackspotpicture137">
    ifnot (hotspot[spotpicture137].flying == 0.0,
      tween(hotspot[spotpicture137].rx, -52.91726261155361);
      tween(hotspot[spotpicture137].ry, 9.7840847346110458);
      tween(hotspot[spotpicture137].rz, 9.2316018589588111);
      tween(hotspot[spotpicture137].width , 45);
      tween(hotspot[spotpicture137].height, 99);
      set(hotspot[spotpicture137].zorder, get(hotspot[spotpicture137].zorder_backup));
      set(hotspot[spotpicture137].zorder2, 0.0);
      setzorder2onstandardspots(1);

      tween(hotspot[spotpicture137].flying, 0.0);
    );
  </action>
  <events name="eventsspotpicture137" onremovedisplayedobject="spotflybackspotpicture137"/>

  <action name="hidepanopicturespots">
    set(hotspot[spotpicture137].visible, false);
  </action>
  <action name="showpanopicturespots">
    set(hotspot[spotpicture137].visible, true);
  </action>

  <!-- **** 3 Point Spots **** -->



  <hotspot name="spotpoint309"
           ath="120.523324" atv="6.019543"
           style="IconLoadpanorama"
           tag="point"
           descriptionid=""
           onclick="onclickspotpoint309"
           tooltip="spotpoint309_tooltip"
           />
  <hotspot name="spotpoint309" devices="flash" zorder="3"/>
  <hotspot name="spotpoint309" devices="html5" zorder="3" zorder2="1"/>
  <action name="onclickspotpoint309">
  
        mainloadscene(pano39);lookat(get(panoview.h), get(panoview.v), get(panoview.fov));


  </action>





  <hotspot name="spotpoint310"
           ath="42.575755" atv="12.039144"
           style="IconLoadpanorama"
           tag="point"
           descriptionid=""
           onclick="onclickspotpoint310"
           tooltip="spotpoint310_tooltip"
           />
  <hotspot name="spotpoint310" devices="flash" zorder="3"/>
  <hotspot name="spotpoint310" devices="html5" zorder="3" zorder2="1"/>
  <action name="onclickspotpoint310">
  
        mainloadscene(pano118);lookat(get(panoview.h), get(panoview.v), get(panoview.fov));


  </action>





  <hotspot name="spotpoint313"
           ath="-131.111280" atv="-8.957471"
           style="IconDisplayanimage1"
           tag="point"
           descriptionid=""
           onclick="onclickspotpoint313"
           />
  <hotspot name="spotpoint313" devices="flash" zorder="3"/>
  <hotspot name="spotpoint313" devices="html5" zorder="3" zorder2="1"/>
  <action name="onclickspotpoint313">
  
displayImage(%FIRSTXML%/spots/info_2.png
             ,center,0,0
             ,'',''
             ,false
             ,false
             ,false
             ,false
             ,000000
             ,0);

  </action>



  <action name="hidepanopointspots">
    set(hotspot[spotpoint309].visible, false);
    set(hotspot[spotpoint310].visible, false);
    set(hotspot[spotpoint313].visible, false);
  </action>
  <action name="showpanopointspots">
    set(hotspot[spotpoint309].visible, true);
    set(hotspot[spotpoint310].visible, true);
    set(hotspot[spotpoint313].visible, true);
  </action>
  <events name="pano38stopanimatedspots" onremovepano="stopspotanimation(spotpoint309);stopspotanimation(spotpoint310);stopspotanimation(spotpoint313);" />


  <action name="showpanospotsaction">
    resumeTourSoundsActions(true,false,false,false,true);
    if (tour_displayspots,
    showpanopointspots();
    showpanopicturespots();
    showpanopolygonalspots();
    );
  </action>
  <action name="hidepanospotsaction">
    pauseTourSoundsActions(true,false,false,false,true);
    hidepanopointspots();
    hidepanopicturespots();
    hidepanopolygonalspots();
  </action>


  <action name="setzorder2onstandardspots">
    if (device.html5,
      ifnot (device.desktop,

        tween(hotspot[spotpolygon114].zorder2, %1);

        tween(hotspot[spotpolygon117].zorder2, %1);


        tween(hotspot[spotpoint309].zorder2, %1);

        tween(hotspot[spotpoint310].zorder2, %1);

        tween(hotspot[spotpoint313].zorder2, %1);

      );
    );
  </action>


</scene>



<!-- **** @PanoName="Зал Рюриковича с братьями" @PanoFile="C:/Users/Сергей/Desktop/Фото Панорам/ATAA4602.JPG" **** -->
<!-- **** Width="0px" Height="0px" **** -->
<scene name="pano118"
       latitude="0"
       longitude="0"
       heading="166.4000000000002"
       group="panogroup40"
       thumburl="%FIRSTXML%/ataa4602_118/thumbnail.jpg"
       backgroundsound=""
       backgroundsoundloops="0"
       haslocalsounds="true"
       haspolygons="true"
       titleid="pano118_title"
       descriptionid="pano118_description"
       multires="true"
       planar="false"
       full360="false"
       video="false"
       seen="false">

    <autorotate horizon="0.000000" tofov="62.718900" waittime="1" speed="5"/>


    <panoview h="-144.870000" v="0.000000" fov="62.718900" hmin="-180" hmax="180" vmin="-31.359449999999999" vmax="31.359449999999999" fovmax="90" />

    <view fisheye="0"
          limitview="range"
          hlookatmin="-180"
          hlookatmax="180"
          vlookatmin="-31.359449999999999"
          vlookatmax="31.359449999999999"
          maxpixelzoom="1.0"
          fovtype="VFOV"
          fovmax="90"
          fov="62.718900"
          hlookat="-144.870000"
          vlookat="0.000000"/>

    <preview url="%FIRSTXML%/ataa4602_118/preview.jpg" type="CUBESTRIP" striporder="FRBLUD" />


        <image type="SPHERE" hfov="360" vfov="62.718899999999998" voffset="0" multires="true" baseindex="0" tilesize="512" devices="flash.and.desktop">
          <level tiledimagewidth="10085" tiledimageheight="1753">
            <sphere url="ataa4602_118/1/%v_%u.jpg"/>
          </level>
          <level tiledimagewidth="5042" tiledimageheight="876">
            <sphere url="ataa4602_118/0/%v_%u.jpg"/>
          </level>
        </image>
  
  <image type="CUBE" devices="desktop.and.html5">
    <front url="ataa4602_118/html5/0.jpg"/>
    <right url="ataa4602_118/html5/1.jpg"/>
    <back  url="ataa4602_118/html5/2.jpg"/>
    <left  url="ataa4602_118/html5/3.jpg"/>
    <up    url="ataa4602_118/html5/4.jpg"/>
    <down  url="ataa4602_118/html5/5.jpg"/>
  </image>
  
      <image type="CUBE" devices="tablet">
        <front url="ataa4602_118/tablet/0.jpg"/>
        <right url="ataa4602_118/tablet/1.jpg"/>
        <back  url="ataa4602_118/tablet/2.jpg"/>
        <left  url="ataa4602_118/tablet/3.jpg"/>
        <up    url="ataa4602_118/tablet/4.jpg"/>
        <down  url="ataa4602_118/tablet/5.jpg"/>
      </image>
      <image type="CUBE" devices="mobile">
        <front url="ataa4602_118/mobile/0.jpg"/>
        <right url="ataa4602_118/mobile/1.jpg"/>
        <back  url="ataa4602_118/mobile/2.jpg"/>
        <left  url="ataa4602_118/mobile/3.jpg"/>
        <up    url="ataa4602_118/mobile/4.jpg"/>
        <down  url="ataa4602_118/mobile/5.jpg"/>
      </image>


  <!-- **** 2 Polygonal Spots **** -->


  <hotspot name="spotpolygon124"
           tag="polygon"
           style="PolygonDefaultPolygonSpotStyle"
           descriptionid=""
           onclick="onclickspotpolygon124"
           tooltip="spotpolygon124_tooltip"
           >
    <point ath="26.018640" atv="7.781471" />
    <point ath="30.963600" atv="17.664026" />
    <point ath="50.287320" atv="12.216952" />
    <point ath="38.267280" atv="8.404019" />
  </hotspot>
  <hotspot name="spotpolygon124" devices="flash" zorder="1"/>
  <hotspot name="spotpolygon124" devices="html5" zorder="3" zorder2="1"/>


  <action name="onclickspotpolygon124">
  
        mainloadscene(pano38);lookat(get(panoview.h), get(panoview.v), get(panoview.fov));


  </action>



  <hotspot name="spotpolygon132"
           tag="polygon"
           style="PolygonDefaultPolygonSpotStyle"
           descriptionid=""
           onclick="onclickspotpolygon132"
           tooltip="spotpolygon132_tooltip"
           >
    <point ath="140.942160" atv="18.454346" />
    <point ath="141.199200" atv="-15.873276" />
    <point ath="153.019440" atv="-13.034179" />
    <point ath="152.762400" atv="11.743675" />
  </hotspot>
  <hotspot name="spotpolygon132" devices="flash" zorder="1"/>
  <hotspot name="spotpolygon132" devices="html5" zorder="3" zorder2="1"/>


  <action name="onclickspotpolygon132">
  
        mainloadscene(pano125);lookat(get(panoview.h), get(panoview.v), get(panoview.fov));


  </action>


  <action name="hidepanopolygonalspots">
    set(hotspot[spotpolygon124].visible, false);
    set(hotspot[spotpolygon132].visible, false);
  </action>
  <action name="showpanopolygonalspots">
    set(hotspot[spotpolygon124].visible, true);
    set(hotspot[spotpolygon132].visible, true);
  </action>
  <action name="removepanopolygonalspots">
    removehotspot(spotpolygon124);
    removehotspot(spotpolygon132);
  </action>

  <!-- **** 1 Video Spots **** -->
  <krpano videospots_playing="0" />


  <hotspot name="spotvideo136"
           style="RectVideoDefaultVideoSpotStyle"
           tag="video"
           descriptionid=""
           ath="115.779522" atv="-7.759689"
           width="565" 
           height="325" 
           rx="-8.0971632629151848" 
           ry="-16.318328467665083" 
           rz="-0.40010314577930872"
           onclick="onclickspotvideo136_stateVideo();onclickspotvideo136(true);"
           onvideoreadyspecific="onvideoreadyspotvideo136"
           posterurl="%FIRSTXML%/spots/drevnii_rus.jpg"
         />
  <hotspot name="spotvideo136" devices="flash" zorder="2"/>
  <hotspot name="spotvideo136" devices="html5" zorder="2"/>
  <hotspot name="spotvideo136" videourl="%FIRSTXML%/spots/drevnii_rus.mp4" devices="desktop" onunsupported="trace('not supported');" />
  <hotspot name="spotvideo136" videourl="%FIRSTXML%/spots/drevnii_rus.mp4" devices="tablet.or.mobile" onunsupported="trace('not supported');" />
  <hotspot name="spotvideo136Loader"
           style="RectVideoDefaultVideoSpotStyleLoader"
           ath="115.779522" atv="-7.759689"
           rx="-8.0971632629151848" 
           ry="-16.318328467665083" 
           rz="-0.40010314577930872" 
           activated="false"
           onloaded="onloadedspotvideo136Loader"
           />

  <action name="onclickspotvideo136_stateVideo">
    if(hotspot[spotvideo136].ispaused,
      set(hotspot[spotvideo136].stateVideo, 'playing');
    ,
      set(hotspot[spotvideo136].stateVideo, 'paused');
    );
  </action>
  <action name="onclickspotvideo136">
    if (hotspot[spotvideo136].alpha == 0, set(hotspot[spotvideo136].alpha, 1););
    hotspot[spotvideo136].togglepause();

  </action>

  <action name="onloadedspotvideo136Loader">
    animatevideospotloaderRectVideoDefaultVideoSpotStyle(spotvideo136Loader, spotvideo136call);
  </action>
  <action name="onvideoreadyspotvideo136">
    stopvideospotloaderanimationRectVideoDefaultVideoSpotStyle(spotvideo136Loader, spotvideo136call);
  </action>


  <action name="hidepanovideospots">
    if (hotspot[spotvideo136Loader] !== null,
      set(hotspot[spotvideo136Loader].activated, false);
      set(hotspot[spotvideo136Loader].visible, false);
    );
    if (hotspot[spotvideo136] !== null,
      set(hotspot[spotvideo136].visible, false);

      ifnot(hotspot[spotvideo136].alpha == 0,
        if (hotspot[spotvideo136].isvideoready,
          if(hotspot[spotvideo136].stateVideo == 'playing',
            dec(videospots_playing);
            onclickspotvideo136(false);
            if(hotspot[spotvideo136].pauseothersounds,
              resumeTourSoundsActions(false,true,true,true,true);
            );
          );
        );
      );
    );
  </action>
  <action name="showpanovideospots">
    if (hotspot[spotvideo136Loader] !== null,
      set(hotspot[spotvideo136Loader].activated, true);
      set(hotspot[spotvideo136Loader].visible, true);
    );
    if (hotspot[spotvideo136] !== null,
      set(hotspot[spotvideo136].visible, true);

      ifnot(hotspot[spotvideo136].alpha == 0,
        if (hotspot[spotvideo136].isvideoready,
          if(hotspot[spotvideo136].stateVideo == 'playing',
            inc(videospots_playing);
            onclickspotvideo136(false);
            if(hotspot[spotvideo136].pauseothersounds,
              pauseTourSoundsActions(true,true,true,true,true);
            );

            if (tour_soundson,
              div(volume, tour_soundsvolume, 100);
              if(device.flash,
                set(hotspot[spotvideo136].volume, get(volume));
              ,
                ifnot(device.ios,
                  js(kpanotour.Sounds.startVideosSounds(get(volume)));
                );
              );
            );
          );
        );
      );
    );
  </action>
  <events name="pano118videospotsevents" 
    onxmlcomplete="set(hotspot[spotvideo136].canstart, false);" 
    onloadcomplete="if(panovideospotsstate,set(hotspot[spotvideo136].canstart, true););" 
    playtoursoundsevent="if(hotspot[spotvideo136].pauseothersounds,if(hotspot[spotvideo136].stateVideo == 'playing',pauseTourSoundsActions(false,true,true,true,true);););" />

  <!-- **** 5 Point Spots **** -->



  <hotspot name="spotpoint311"
           ath="34.762673" atv="11.451093"
           style="IconLoadpanorama"
           tag="point"
           descriptionid=""
           onclick="onclickspotpoint311"
           tooltip="spotpoint311_tooltip"
           />
  <hotspot name="spotpoint311" devices="flash" zorder="3"/>
  <hotspot name="spotpoint311" devices="html5" zorder="3" zorder2="1"/>
  <action name="onclickspotpoint311">
  
        mainloadscene(pano38);lookat(get(panoview.h), get(panoview.v), get(panoview.fov));


  </action>





  <hotspot name="spotpoint312"
           ath="146.415610" atv="2.769226"
           style="IconLoadpanorama"
           tag="point"
           descriptionid=""
           onclick="onclickspotpoint312"
           tooltip="spotpoint312_tooltip"
           />
  <hotspot name="spotpoint312" devices="flash" zorder="3"/>
  <hotspot name="spotpoint312" devices="html5" zorder="3" zorder2="1"/>
  <action name="onclickspotpoint312">
  
        mainloadscene(pano125);lookat(get(panoview.h), get(panoview.v), get(panoview.fov));


  </action>





  <hotspot name="spotpoint365"
           ath="-162.691379" atv="-6.804436"
           style="IconDisplayanimage1"
           tag="point"
           descriptionid=""
           onclick="onclickspotpoint365"
           />
  <hotspot name="spotpoint365" devices="flash" zorder="3"/>
  <hotspot name="spotpoint365" devices="html5" zorder="3" zorder2="1"/>
  <action name="onclickspotpoint365">
  
displayImage(%FIRSTXML%/spots/info_3.png
             ,center,0,0
             ,'',''
             ,false
             ,false
             ,false
             ,false
             ,000000
             ,0);

  </action>





  <hotspot name="spotpoint366"
           ath="-135.132839" atv="-3.845985"
           style="IconDisplayanimage1"
           tag="point"
           descriptionid=""
           onclick="onclickspotpoint366"
           />
  <hotspot name="spotpoint366" devices="flash" zorder="3"/>
  <hotspot name="spotpoint366" devices="html5" zorder="3" zorder2="1"/>
  <action name="onclickspotpoint366">
  
displayImage(%FIRSTXML%/spots/info_4.png
             ,center,0,0
             ,'',''
             ,false
             ,false
             ,false
             ,false
             ,000000
             ,0);

  </action>





  <hotspot name="spotpoint367"
           ath="-2.949121" atv="-10.058669"
           style="IconDisplayanimage1"
           tag="point"
           descriptionid=""
           onclick="onclickspotpoint367"
           />
  <hotspot name="spotpoint367" devices="flash" zorder="3"/>
  <hotspot name="spotpoint367" devices="html5" zorder="3" zorder2="1"/>
  <action name="onclickspotpoint367">
  
displayImage(%FIRSTXML%/spots/info_5.png
             ,center,0,0
             ,'',''
             ,false
             ,false
             ,false
             ,false
             ,000000
             ,0);

  </action>



  <action name="hidepanopointspots">
    set(hotspot[spotpoint311].visible, false);
    set(hotspot[spotpoint312].visible, false);
    set(hotspot[spotpoint365].visible, false);
    set(hotspot[spotpoint366].visible, false);
    set(hotspot[spotpoint367].visible, false);
  </action>
  <action name="showpanopointspots">
    set(hotspot[spotpoint311].visible, true);
    set(hotspot[spotpoint312].visible, true);
    set(hotspot[spotpoint365].visible, true);
    set(hotspot[spotpoint366].visible, true);
    set(hotspot[spotpoint367].visible, true);
  </action>
  <events name="pano118stopanimatedspots" onremovepano="stopspotanimation(spotpoint311);stopspotanimation(spotpoint312);stopspotanimation(spotpoint365);stopspotanimation(spotpoint366);stopspotanimation(spotpoint367);" />


  <action name="showpanospotsaction">
    resumeTourSoundsActions(true,false,false,false,true);
    if (tour_displayspots,
    showpanopointspots();
    showpanovideospots();
    showpanopolygonalspots();
    );
  </action>
  <action name="hidepanospotsaction">
    pauseTourSoundsActions(true,false,false,false,true);
    hidepanopointspots();
    hidepanovideospots();
    hidepanopolygonalspots();
  </action>

  <!-- **** 0 Directional Sound Spots **** -->
  <action name="playpanolocalsounds">
    if (tour_soundson,
      div(volume, tour_soundsvolume, 100);
      if(device.flash,
        set(hotspot[spotvideo136].volume, get(volume));
      ,
        ifnot(device.ios,
          js(kpanotour.Sounds.startVideosSounds(get(volume)));
        );
      );
     ,
      if(device.flash,
        set(hotspot[spotvideo136].volume, 0); 
      ,
        ifnot(device.ios,
          js(kpanotour.Sounds.stopVideosSounds());
        );
      );
    );
  </action>
  <action name="stoppanolocalsounds">
    if(device.flash,
      set(hotspot[spotvideo136].volume, 0);
    ,
      ifnot(device.ios,
        js(kpanotour.Sounds.stopVideosSounds());
      );
    );
  </action>
  <action name="setpanolocalsoundsvolume">
    if (tour_soundson,
      div(volume, tour_soundsvolume, 100);
      if(device.flash,
        set(hotspot[spotvideo136].volume, get(volume));
      ,
        ifnot(device.ios,
          js(kpanotour.Sounds.startVideosSounds(get(volume)));
        );
      );
    );
  </action>
  <action name="pausepanolocalsounds">
    if(device.flash,
      set(hotspot[spotvideo136].volume, 0);
    ,
      ifnot(device.ios,
        js(kpanotour.Sounds.stopVideosSounds());
      );
    );
  </action>
  <action name="resumepanolocalsounds">
    if(tour_soundson,
      div(volume, tour_soundsvolume, 100);
      if(device.flash,
        set(hotspot[spotvideo136].volume, get(volume));
      ,
        ifnot(device.ios,
          js(kpanotour.Sounds.startVideosSounds(get(volume)));
        );
      );
    ,
      if(device.flash,
        set(hotspot[spotvideo136].volume, 0);
      ,
        ifnot(device.ios,
          js(kpanotour.Sounds.stopVideosSounds(get(volume)));
        );
      );
    );
  </action>
  <events name="pano118soundsevents" onnewpano="playpanolocalsounds();" />


  <action name="setzorder2onstandardspots">
    if (device.html5,
      ifnot (device.desktop,

        tween(hotspot[spotpolygon124].zorder2, %1);

        tween(hotspot[spotpolygon132].zorder2, %1);


        tween(hotspot[spotpoint311].zorder2, %1);

        tween(hotspot[spotpoint312].zorder2, %1);

        tween(hotspot[spotpoint365].zorder2, %1);

        tween(hotspot[spotpoint366].zorder2, %1);

        tween(hotspot[spotpoint367].zorder2, %1);

      );
    );
  </action>


</scene>



<!-- **** @PanoName="Зал с князем Владимиром" @PanoFile="C:/Users/Сергей/Desktop/Фото Панорам/SOHT3110.JPG" **** -->
<!-- **** Width="0px" Height="0px" **** -->
<scene name="pano125"
       latitude="0"
       longitude="0"
       heading="75.400000000000489"
       group="panogroup40"
       thumburl="%FIRSTXML%/photopano_4_125/thumbnail.jpg"
       backgroundsound=""
       backgroundsoundloops="0"
       haslocalsounds="false"
       haspolygons="true"
       titleid="pano125_title"
       descriptionid="pano125_description"
       multires="true"
       planar="false"
       full360="false"
       video="false"
       seen="false">

    <autorotate horizon="0.000000" tofov="61.869900" waittime="1" speed="5"/>


    <panoview h="-168.510000" v="0.000000" fov="61.869900" hmin="-180" hmax="180" vmin="-30.934950000000001" vmax="30.934950000000001" fovmax="90" />

    <view fisheye="0"
          limitview="range"
          hlookatmin="-180"
          hlookatmax="180"
          vlookatmin="-30.934950000000001"
          vlookatmax="30.934950000000001"
          maxpixelzoom="1.0"
          fovtype="VFOV"
          fovmax="90"
          fov="61.869900"
          hlookat="-168.510000"
          vlookat="0.000000"/>

    <preview url="%FIRSTXML%/photopano_4_125/preview.jpg" type="CUBESTRIP" striporder="FRBLUD" />


        <image type="SPHERE" hfov="360" vfov="61.869900000000001" voffset="0" multires="true" baseindex="0" tilesize="512" devices="flash.and.desktop">
          <level tiledimagewidth="9915" tiledimageheight="1699">
            <sphere url="photopano_4_125/1/%v_%u.jpg"/>
          </level>
          <level tiledimagewidth="4957" tiledimageheight="849">
            <sphere url="photopano_4_125/0/%v_%u.jpg"/>
          </level>
        </image>
  
  <image type="CUBE" devices="desktop.and.html5">
    <front url="photopano_4_125/html5/0.jpg"/>
    <right url="photopano_4_125/html5/1.jpg"/>
    <back  url="photopano_4_125/html5/2.jpg"/>
    <left  url="photopano_4_125/html5/3.jpg"/>
    <up    url="photopano_4_125/html5/4.jpg"/>
    <down  url="photopano_4_125/html5/5.jpg"/>
  </image>
  
      <image type="CUBE" devices="tablet">
        <front url="photopano_4_125/tablet/0.jpg"/>
        <right url="photopano_4_125/tablet/1.jpg"/>
        <back  url="photopano_4_125/tablet/2.jpg"/>
        <left  url="photopano_4_125/tablet/3.jpg"/>
        <up    url="photopano_4_125/tablet/4.jpg"/>
        <down  url="photopano_4_125/tablet/5.jpg"/>
      </image>
      <image type="CUBE" devices="mobile">
        <front url="photopano_4_125/mobile/0.jpg"/>
        <right url="photopano_4_125/mobile/1.jpg"/>
        <back  url="photopano_4_125/mobile/2.jpg"/>
        <left  url="photopano_4_125/mobile/3.jpg"/>
        <up    url="photopano_4_125/mobile/4.jpg"/>
        <down  url="photopano_4_125/mobile/5.jpg"/>
      </image>


  <!-- **** 1 Polygonal Spots **** -->


  <hotspot name="spotpolygon131"
           tag="polygon"
           style="PolygonDefaultPolygonSpotStyle"
           descriptionid=""
           onclick="onclickspotpolygon131"
           tooltip="spotpolygon131_tooltip"
           >
    <point ath="4.370760" atv="8.422102" />
    <point ath="-8.185320" atv="30.610999" />
    <point ath="48.556440" atv="29.963159" />
    <point ath="47.920680" atv="7.450311" />
  </hotspot>
  <hotspot name="spotpolygon131" devices="flash" zorder="1"/>
  <hotspot name="spotpolygon131" devices="html5" zorder="3" zorder2="1"/>


  <action name="onclickspotpolygon131">
  
        mainloadscene(pano118);lookat(get(panoview.h), get(panoview.v), get(panoview.fov));


  </action>


  <action name="hidepanopolygonalspots">
    set(hotspot[spotpolygon131].visible, false);
  </action>
  <action name="showpanopolygonalspots">
    set(hotspot[spotpolygon131].visible, true);
  </action>
  <action name="removepanopolygonalspots">
    removehotspot(spotpolygon131);
  </action>

  <!-- **** 3 Point Spots **** -->



  <hotspot name="spotpoint368"
           ath="21.367443" atv="18.146193"
           style="IconLoadpanorama"
           tag="point"
           descriptionid=""
           onclick="onclickspotpoint368"
           tooltip="spotpoint368_tooltip"
           />
  <hotspot name="spotpoint368" devices="flash" zorder="3"/>
  <hotspot name="spotpoint368" devices="html5" zorder="3" zorder2="1"/>
  <action name="onclickspotpoint368">
  
        mainloadscene(pano118);lookat(get(panoview.h), get(panoview.v), get(panoview.fov));


  </action>





  <hotspot name="spotpoint369"
           ath="-169.059816" atv="-4.320499"
           style="IconDisplayanimage1"
           tag="point"
           descriptionid=""
           onclick="onclickspotpoint369"
           />
  <hotspot name="spotpoint369" devices="flash" zorder="3"/>
  <hotspot name="spotpoint369" devices="html5" zorder="3" zorder2="1"/>
  <action name="onclickspotpoint369">
  
displayImage(%FIRSTXML%/spots/info_6.png
             ,center,0,0
             ,'',''
             ,false
             ,false
             ,false
             ,false
             ,000000
             ,0);

  </action>





  <hotspot name="spotpoint373"
           ath="131.970241" atv="5.231658"
           style="IconLoadpanorama"
           tag="point"
           descriptionid=""
           onclick="onclickspotpoint373"
           tooltip="spotpoint373_tooltip"
           />
  <hotspot name="spotpoint373" devices="flash" zorder="3"/>
  <hotspot name="spotpoint373" devices="html5" zorder="3" zorder2="1"/>
  <action name="onclickspotpoint373">
  
        mainloadscene(pano370);lookat(get(panoview.h), get(panoview.v), get(panoview.fov));


  </action>



  <action name="hidepanopointspots">
    set(hotspot[spotpoint368].visible, false);
    set(hotspot[spotpoint369].visible, false);
    set(hotspot[spotpoint373].visible, false);
  </action>
  <action name="showpanopointspots">
    set(hotspot[spotpoint368].visible, true);
    set(hotspot[spotpoint369].visible, true);
    set(hotspot[spotpoint373].visible, true);
  </action>
  <events name="pano125stopanimatedspots" onremovepano="stopspotanimation(spotpoint368);stopspotanimation(spotpoint369);stopspotanimation(spotpoint373);" />


  <action name="showpanospotsaction">
    resumeTourSoundsActions(true,false,false,false,true);
    if (tour_displayspots,
    showpanopointspots();
    showpanopolygonalspots();
    );
  </action>
  <action name="hidepanospotsaction">
    pauseTourSoundsActions(true,false,false,false,true);
    hidepanopointspots();
    hidepanopolygonalspots();
  </action>


  <action name="setzorder2onstandardspots">
    if (device.html5,
      ifnot (device.desktop,

        tween(hotspot[spotpolygon131].zorder2, %1);


        tween(hotspot[spotpoint368].zorder2, %1);

        tween(hotspot[spotpoint369].zorder2, %1);

        tween(hotspot[spotpoint373].zorder2, %1);

      );
    );
  </action>


</scene>



<!-- **** @PanoName="Зал Князя-Миротворца" @PanoFile="D:/Panorama/Image/CZHZ7289.JPG" **** -->
<!-- **** Width="0px" Height="0px" **** -->
<scene name="pano370"
       latitude="0"
       longitude="0"
       heading="4.8000000000010914"
       group="panogroup40"
       thumburl="%FIRSTXML%/czhz7289_370/thumbnail.jpg"
       backgroundsound=""
       backgroundsoundloops="0"
       haslocalsounds="false"
       haspolygons="false"
       titleid="pano370_title"
       descriptionid=""
       multires="true"
       planar="false"
       full360="false"
       video="false"
       seen="false">

    <autorotate horizon="0.000000" tofov="62.544400" waittime="1" speed="5"/>


    <panoview h="164.490000" v="0.000000" fov="62.544400" hmin="-180" hmax="180" vmin="-31.272200000000002" vmax="31.272200000000002" fovmax="90" />

    <view fisheye="0"
          limitview="range"
          hlookatmin="-180"
          hlookatmax="180"
          vlookatmin="-31.272200000000002"
          vlookatmax="31.272200000000002"
          maxpixelzoom="1.0"
          fovtype="VFOV"
          fovmax="90"
          fov="62.544400"
          hlookat="164.490000"
          vlookat="0.000000"/>

    <preview url="%FIRSTXML%/czhz7289_370/preview.jpg" type="CUBESTRIP" striporder="FRBLUD" />


        <image type="SPHERE" hfov="360" vfov="62.544400000000003" voffset="0" multires="true" baseindex="0" tilesize="512" devices="flash.and.desktop">
          <level tiledimagewidth="9975" tiledimageheight="1729">
            <sphere url="czhz7289_370/1/%v_%u.jpg"/>
          </level>
          <level tiledimagewidth="4987" tiledimageheight="864">
            <sphere url="czhz7289_370/0/%v_%u.jpg"/>
          </level>
        </image>
  
  <image type="CUBE" devices="desktop.and.html5">
    <front url="czhz7289_370/html5/0.jpg"/>
    <right url="czhz7289_370/html5/1.jpg"/>
    <back  url="czhz7289_370/html5/2.jpg"/>
    <left  url="czhz7289_370/html5/3.jpg"/>
    <up    url="czhz7289_370/html5/4.jpg"/>
    <down  url="czhz7289_370/html5/5.jpg"/>
  </image>
  
      <image type="CUBE" devices="tablet">
        <front url="czhz7289_370/tablet/0.jpg"/>
        <right url="czhz7289_370/tablet/1.jpg"/>
        <back  url="czhz7289_370/tablet/2.jpg"/>
        <left  url="czhz7289_370/tablet/3.jpg"/>
        <up    url="czhz7289_370/tablet/4.jpg"/>
        <down  url="czhz7289_370/tablet/5.jpg"/>
      </image>
      <image type="CUBE" devices="mobile">
        <front url="czhz7289_370/mobile/0.jpg"/>
        <right url="czhz7289_370/mobile/1.jpg"/>
        <back  url="czhz7289_370/mobile/2.jpg"/>
        <left  url="czhz7289_370/mobile/3.jpg"/>
        <up    url="czhz7289_370/mobile/4.jpg"/>
        <down  url="czhz7289_370/mobile/5.jpg"/>
      </image>


  <!-- **** 2 Point Spots **** -->



  <hotspot name="spotpoint374"
           ath="41.384876" atv="9.419311"
           style="IconLoadpanorama"
           tag="point"
           descriptionid=""
           onclick="onclickspotpoint374"
           tooltip="spotpoint374_tooltip"
           />
  <hotspot name="spotpoint374" devices="flash" zorder="3"/>
  <hotspot name="spotpoint374" devices="html5" zorder="3" zorder2="1"/>
  <action name="onclickspotpoint374">
  
        mainloadscene(pano125);lookat(get(panoview.h), get(panoview.v), get(panoview.fov));


  </action>





  <hotspot name="spotpoint427"
           ath="163.931766" atv="2.937148"
           style="IconLoadpanorama"
           tag="point"
           descriptionid=""
           onclick="onclickspotpoint427"
           tooltip="spotpoint427_tooltip"
           />
  <hotspot name="spotpoint427" devices="flash" zorder="3"/>
  <hotspot name="spotpoint427" devices="html5" zorder="3" zorder2="1"/>
  <action name="onclickspotpoint427">
  
        mainloadscene(pano415);lookat(get(panoview.h), get(panoview.v), get(panoview.fov));


  </action>



  <action name="hidepanopointspots">
    set(hotspot[spotpoint374].visible, false);
    set(hotspot[spotpoint427].visible, false);
  </action>
  <action name="showpanopointspots">
    set(hotspot[spotpoint374].visible, true);
    set(hotspot[spotpoint427].visible, true);
  </action>
  <events name="pano370stopanimatedspots" onremovepano="stopspotanimation(spotpoint374);stopspotanimation(spotpoint427);" />


  <action name="showpanospotsaction">
    resumeTourSoundsActions(true,false,false,false,true);
    if (tour_displayspots,
    showpanopointspots();
    );
  </action>
  <action name="hidepanospotsaction">
    pauseTourSoundsActions(true,false,false,false,true);
    hidepanopointspots();
  </action>


  <action name="setzorder2onstandardspots">
    if (device.html5,
      ifnot (device.desktop,


        tween(hotspot[spotpoint374].zorder2, %1);

        tween(hotspot[spotpoint427].zorder2, %1);

      );
    );
  </action>


</scene>



<!-- **** @PanoName="Зал Раздробленности" @PanoFile="D:/Panorama/Image/XPGV3242.JPG" **** -->
<!-- **** Width="0px" Height="0px" **** -->
<scene name="pano415"
       latitude="0"
       longitude="0"
       heading="-8.5999999999998522"
       group="panogroup40"
       thumburl="%FIRSTXML%/pano_415/thumbnail.jpg"
       backgroundsound=""
       backgroundsoundloops="0"
       haslocalsounds="false"
       haspolygons="false"
       titleid="pano415_title"
       descriptionid=""
       multires="true"
       planar="false"
       full360="false"
       video="false"
       seen="false">

    <autorotate horizon="0.000000" tofov="62.718900" waittime="1" speed="5"/>


    <panoview h="-166.510000" v="0.000000" fov="62.718900" hmin="-180" hmax="180" vmin="-31.359449999999999" vmax="31.359449999999999" fovmax="90" />

    <view fisheye="0"
          limitview="range"
          hlookatmin="-180"
          hlookatmax="180"
          vlookatmin="-31.359449999999999"
          vlookatmax="31.359449999999999"
          maxpixelzoom="1.0"
          fovtype="VFOV"
          fovmax="90"
          fov="62.718900"
          hlookat="-166.510000"
          vlookat="0.000000"/>

    <preview url="%FIRSTXML%/pano_415/preview.jpg" type="CUBESTRIP" striporder="FRBLUD" />


        <image type="SPHERE" hfov="360" vfov="62.718899999999998" voffset="0" multires="true" baseindex="0" tilesize="512" devices="flash.and.desktop">
          <level tiledimagewidth="10085" tiledimageheight="1753">
            <sphere url="pano_415/1/%v_%u.jpg"/>
          </level>
          <level tiledimagewidth="5042" tiledimageheight="876">
            <sphere url="pano_415/0/%v_%u.jpg"/>
          </level>
        </image>
  
  <image type="CUBE" devices="desktop.and.html5">
    <front url="pano_415/html5/0.jpg"/>
    <right url="pano_415/html5/1.jpg"/>
    <back  url="pano_415/html5/2.jpg"/>
    <left  url="pano_415/html5/3.jpg"/>
    <up    url="pano_415/html5/4.jpg"/>
    <down  url="pano_415/html5/5.jpg"/>
  </image>
  
      <image type="CUBE" devices="tablet">
        <front url="pano_415/tablet/0.jpg"/>
        <right url="pano_415/tablet/1.jpg"/>
        <back  url="pano_415/tablet/2.jpg"/>
        <left  url="pano_415/tablet/3.jpg"/>
        <up    url="pano_415/tablet/4.jpg"/>
        <down  url="pano_415/tablet/5.jpg"/>
      </image>
      <image type="CUBE" devices="mobile">
        <front url="pano_415/mobile/0.jpg"/>
        <right url="pano_415/mobile/1.jpg"/>
        <back  url="pano_415/mobile/2.jpg"/>
        <left  url="pano_415/mobile/3.jpg"/>
        <up    url="pano_415/mobile/4.jpg"/>
        <down  url="pano_415/mobile/5.jpg"/>
      </image>


  <!-- **** 2 Point Spots **** -->



  <hotspot name="spotpoint428"
           ath="7.008483" atv="9.649053"
           style="IconLoadpanorama"
           tag="point"
           descriptionid=""
           onclick="onclickspotpoint428"
           tooltip="spotpoint428_tooltip"
           />
  <hotspot name="spotpoint428" devices="flash" zorder="3"/>
  <hotspot name="spotpoint428" devices="html5" zorder="3" zorder2="1"/>
  <action name="onclickspotpoint428">
  
        mainloadscene(pano370);lookat(get(panoview.h), get(panoview.v), get(panoview.fov));


  </action>





  <hotspot name="spotpoint431"
           ath="-80.170916" atv="11.372128"
           style="IconLoadpanorama"
           tag="point"
           descriptionid=""
           onclick="onclickspotpoint431"
           tooltip="spotpoint431_tooltip"
           />
  <hotspot name="spotpoint431" devices="flash" zorder="3"/>
  <hotspot name="spotpoint431" devices="html5" zorder="3" zorder2="1"/>
  <action name="onclickspotpoint431">
  
        mainloadscene(pano406);lookat(get(panoview.h), get(panoview.v), get(panoview.fov));


  </action>



  <action name="hidepanopointspots">
    set(hotspot[spotpoint428].visible, false);
    set(hotspot[spotpoint431].visible, false);
  </action>
  <action name="showpanopointspots">
    set(hotspot[spotpoint428].visible, true);
    set(hotspot[spotpoint431].visible, true);
  </action>
  <events name="pano415stopanimatedspots" onremovepano="stopspotanimation(spotpoint428);stopspotanimation(spotpoint431);" />


  <action name="showpanospotsaction">
    resumeTourSoundsActions(true,false,false,false,true);
    if (tour_displayspots,
    showpanopointspots();
    );
  </action>
  <action name="hidepanospotsaction">
    pauseTourSoundsActions(true,false,false,false,true);
    hidepanopointspots();
  </action>


  <action name="setzorder2onstandardspots">
    if (device.html5,
      ifnot (device.desktop,


        tween(hotspot[spotpoint428].zorder2, %1);

        tween(hotspot[spotpoint431].zorder2, %1);

      );
    );
  </action>


</scene>



<!-- **** @PanoName="Зал про Русь под Властью Орды" @PanoFile="D:/Panorama/Image/DGEA8011.JPG" **** -->
<!-- **** Width="0px" Height="0px" **** -->
<scene name="pano406"
       latitude="0"
       longitude="0"
       heading="83.19999999999925"
       group="panogroup40"
       thumburl="%FIRSTXML%/pano_406/thumbnail.jpg"
       backgroundsound=""
       backgroundsoundloops="0"
       haslocalsounds="false"
       haspolygons="false"
       titleid="pano406_title"
       descriptionid=""
       multires="true"
       planar="false"
       full360="false"
       video="false"
       seen="false">

    <autorotate horizon="0.000000" tofov="60.886100" waittime="1" speed="5"/>


    <panoview h="-168.510000" v="0.000000" fov="60.886100" hmin="-180" hmax="180" vmin="-30.443049999999999" vmax="30.443049999999999" fovmax="90" />

    <view fisheye="0"
          limitview="range"
          hlookatmin="-180"
          hlookatmax="180"
          vlookatmin="-30.443049999999999"
          vlookatmax="30.443049999999999"
          maxpixelzoom="1.0"
          fovtype="VFOV"
          fovmax="90"
          fov="60.886100"
          hlookat="-168.510000"
          vlookat="0.000000"/>

    <preview url="%FIRSTXML%/pano_406/preview.jpg" type="CUBESTRIP" striporder="FRBLUD" />


        <image type="SPHERE" hfov="360" vfov="60.886099999999999" voffset="0" multires="true" baseindex="0" tilesize="512" devices="flash.and.desktop">
          <level tiledimagewidth="10022" tiledimageheight="1693">
            <sphere url="pano_406/1/%v_%u.jpg"/>
          </level>
          <level tiledimagewidth="5011" tiledimageheight="846">
            <sphere url="pano_406/0/%v_%u.jpg"/>
          </level>
        </image>
  
  <image type="CUBE" devices="desktop.and.html5">
    <front url="pano_406/html5/0.jpg"/>
    <right url="pano_406/html5/1.jpg"/>
    <back  url="pano_406/html5/2.jpg"/>
    <left  url="pano_406/html5/3.jpg"/>
    <up    url="pano_406/html5/4.jpg"/>
    <down  url="pano_406/html5/5.jpg"/>
  </image>
  
      <image type="CUBE" devices="tablet">
        <front url="pano_406/tablet/0.jpg"/>
        <right url="pano_406/tablet/1.jpg"/>
        <back  url="pano_406/tablet/2.jpg"/>
        <left  url="pano_406/tablet/3.jpg"/>
        <up    url="pano_406/tablet/4.jpg"/>
        <down  url="pano_406/tablet/5.jpg"/>
      </image>
      <image type="CUBE" devices="mobile">
        <front url="pano_406/mobile/0.jpg"/>
        <right url="pano_406/mobile/1.jpg"/>
        <back  url="pano_406/mobile/2.jpg"/>
        <left  url="pano_406/mobile/3.jpg"/>
        <up    url="pano_406/mobile/4.jpg"/>
        <down  url="pano_406/mobile/5.jpg"/>
      </image>


  <!-- **** 2 Point Spots **** -->



  <hotspot name="spotpoint433"
           ath="13.846314" atv="14.619545"
           style="IconLoadpanorama"
           tag="point"
           descriptionid=""
           onclick="onclickspotpoint433"
           tooltip="spotpoint433_tooltip"
           />
  <hotspot name="spotpoint433" devices="flash" zorder="3"/>
  <hotspot name="spotpoint433" devices="html5" zorder="3" zorder2="1"/>
  <action name="onclickspotpoint433">
  
        mainloadscene(pano415);lookat(get(panoview.h), get(panoview.v), get(panoview.fov));


  </action>





  <hotspot name="spotpoint434"
           ath="-166.666680" atv="4.643844"
           style="IconLoadpanorama"
           tag="point"
           descriptionid=""
           onclick="onclickspotpoint434"
           tooltip="spotpoint434_tooltip"
           />
  <hotspot name="spotpoint434" devices="flash" zorder="3"/>
  <hotspot name="spotpoint434" devices="html5" zorder="3" zorder2="1"/>
  <action name="onclickspotpoint434">
  
        mainloadscene(pano409);lookat(get(panoview.h), get(panoview.v), get(panoview.fov));


  </action>



  <action name="hidepanopointspots">
    set(hotspot[spotpoint433].visible, false);
    set(hotspot[spotpoint434].visible, false);
  </action>
  <action name="showpanopointspots">
    set(hotspot[spotpoint433].visible, true);
    set(hotspot[spotpoint434].visible, true);
  </action>
  <events name="pano406stopanimatedspots" onremovepano="stopspotanimation(spotpoint433);stopspotanimation(spotpoint434);" />


  <action name="showpanospotsaction">
    resumeTourSoundsActions(true,false,false,false,true);
    if (tour_displayspots,
    showpanopointspots();
    );
  </action>
  <action name="hidepanospotsaction">
    pauseTourSoundsActions(true,false,false,false,true);
    hidepanopointspots();
  </action>


  <action name="setzorder2onstandardspots">
    if (device.html5,
      ifnot (device.desktop,


        tween(hotspot[spotpoint433].zorder2, %1);

        tween(hotspot[spotpoint434].zorder2, %1);

      );
    );
  </action>


</scene>



<!-- **** @PanoName="Зал Александра Невского" @PanoFile="D:/Panorama/Image/IMGH4975.JPG" **** -->
<!-- **** Width="0px" Height="0px" **** -->
<scene name="pano409"
       latitude="0"
       longitude="0"
       heading="80.999999999999943"
       group="panogroup40"
       thumburl="%FIRSTXML%/pano_409/thumbnail.jpg"
       backgroundsound=""
       backgroundsoundloops="0"
       haslocalsounds="false"
       haspolygons="false"
       titleid="pano409_title"
       descriptionid=""
       multires="true"
       planar="false"
       full360="false"
       video="false"
       seen="false">

    <autorotate horizon="0.000000" tofov="61.357200" waittime="1" speed="5"/>


    <panoview h="-169.790000" v="0.000000" fov="61.357200" hmin="-180" hmax="180" vmin="-30.678599999999999" vmax="30.678599999999999" fovmax="90" />

    <view fisheye="0"
          limitview="range"
          hlookatmin="-180"
          hlookatmax="180"
          vlookatmin="-30.678599999999999"
          vlookatmax="30.678599999999999"
          maxpixelzoom="1.0"
          fovtype="VFOV"
          fovmax="90"
          fov="61.357200"
          hlookat="-169.790000"
          vlookat="0.000000"/>

    <preview url="%FIRSTXML%/pano_409/preview.jpg" type="CUBESTRIP" striporder="FRBLUD" />


        <image type="SPHERE" hfov="360" vfov="61.357199999999999" voffset="0" multires="true" baseindex="0" tilesize="512" devices="flash.and.desktop">
          <level tiledimagewidth="10168" tiledimageheight="1732">
            <sphere url="pano_409/1/%v_%u.jpg"/>
          </level>
          <level tiledimagewidth="5084" tiledimageheight="866">
            <sphere url="pano_409/0/%v_%u.jpg"/>
          </level>
        </image>
  
  <image type="CUBE" devices="desktop.and.html5">
    <front url="pano_409/html5/0.jpg"/>
    <right url="pano_409/html5/1.jpg"/>
    <back  url="pano_409/html5/2.jpg"/>
    <left  url="pano_409/html5/3.jpg"/>
    <up    url="pano_409/html5/4.jpg"/>
    <down  url="pano_409/html5/5.jpg"/>
  </image>
  
      <image type="CUBE" devices="tablet">
        <front url="pano_409/tablet/0.jpg"/>
        <right url="pano_409/tablet/1.jpg"/>
        <back  url="pano_409/tablet/2.jpg"/>
        <left  url="pano_409/tablet/3.jpg"/>
        <up    url="pano_409/tablet/4.jpg"/>
        <down  url="pano_409/tablet/5.jpg"/>
      </image>
      <image type="CUBE" devices="mobile">
        <front url="pano_409/mobile/0.jpg"/>
        <right url="pano_409/mobile/1.jpg"/>
        <back  url="pano_409/mobile/2.jpg"/>
        <left  url="pano_409/mobile/3.jpg"/>
        <up    url="pano_409/mobile/4.jpg"/>
        <down  url="pano_409/mobile/5.jpg"/>
      </image>


  <!-- **** 2 Point Spots **** -->



  <hotspot name="spotpoint436"
           ath="6.666834" atv="10.341080"
           style="IconLoadpanorama"
           tag="point"
           descriptionid=""
           onclick="onclickspotpoint436"
           tooltip="spotpoint436_tooltip"
           />
  <hotspot name="spotpoint436" devices="flash" zorder="3"/>
  <hotspot name="spotpoint436" devices="html5" zorder="3" zorder2="1"/>
  <action name="onclickspotpoint436">
  
        mainloadscene(pano406);lookat(get(panoview.h), get(panoview.v), get(panoview.fov));


  </action>





  <hotspot name="spotpoint437"
           ath="-157.435884" atv="10.685787"
           style="IconLoadpanorama"
           tag="point"
           descriptionid=""
           onclick="onclickspotpoint437"
           tooltip="spotpoint437_tooltip"
           />
  <hotspot name="spotpoint437" devices="flash" zorder="3"/>
  <hotspot name="spotpoint437" devices="html5" zorder="3" zorder2="1"/>
  <action name="onclickspotpoint437">
  
        mainloadscene(pano412);lookat(get(panoview.h), get(panoview.v), get(panoview.fov));


  </action>



  <action name="hidepanopointspots">
    set(hotspot[spotpoint436].visible, false);
    set(hotspot[spotpoint437].visible, false);
  </action>
  <action name="showpanopointspots">
    set(hotspot[spotpoint436].visible, true);
    set(hotspot[spotpoint437].visible, true);
  </action>
  <events name="pano409stopanimatedspots" onremovepano="stopspotanimation(spotpoint436);stopspotanimation(spotpoint437);" />


  <action name="showpanospotsaction">
    resumeTourSoundsActions(true,false,false,false,true);
    if (tour_displayspots,
    showpanopointspots();
    );
  </action>
  <action name="hidepanospotsaction">
    pauseTourSoundsActions(true,false,false,false,true);
    hidepanopointspots();
  </action>


  <action name="setzorder2onstandardspots">
    if (device.html5,
      ifnot (device.desktop,


        tween(hotspot[spotpoint436].zorder2, %1);

        tween(hotspot[spotpoint437].zorder2, %1);

      );
    );
  </action>


</scene>



<!-- **** @PanoName="Зал усиления Москвы" @PanoFile="D:/Panorama/Image/ISZV8003.JPG" **** -->
<!-- **** Width="0px" Height="0px" **** -->
<scene name="pano412"
       latitude="0"
       longitude="0"
       heading="83.600000000000875"
       group="panogroup40"
       thumburl="%FIRSTXML%/pano_412/thumbnail.jpg"
       backgroundsound=""
       backgroundsoundloops="0"
       haslocalsounds="false"
       haspolygons="false"
       titleid="pano412_title"
       descriptionid=""
       multires="true"
       planar="false"
       full360="false"
       video="false"
       seen="false">

    <autorotate horizon="0.000000" tofov="62.740800" waittime="1" speed="5"/>


    <panoview h="-168.330000" v="0.000000" fov="62.740800" hmin="-180" hmax="180" vmin="-31.3704" vmax="31.3704" fovmax="90" />

    <view fisheye="0"
          limitview="range"
          hlookatmin="-180"
          hlookatmax="180"
          vlookatmin="-31.3704"
          vlookatmax="31.3704"
          maxpixelzoom="1.0"
          fovtype="VFOV"
          fovmax="90"
          fov="62.740800"
          hlookat="-168.330000"
          vlookat="0.000000"/>

    <preview url="%FIRSTXML%/pano_412/preview.jpg" type="CUBESTRIP" striporder="FRBLUD" />


        <image type="SPHERE" hfov="360" vfov="62.7408" voffset="0" multires="true" baseindex="0" tilesize="512" devices="flash.and.desktop">
          <level tiledimagewidth="10070" tiledimageheight="1750">
            <sphere url="pano_412/1/%v_%u.jpg"/>
          </level>
          <level tiledimagewidth="5035" tiledimageheight="875">
            <sphere url="pano_412/0/%v_%u.jpg"/>
          </level>
        </image>
  
  <image type="CUBE" devices="desktop.and.html5">
    <front url="pano_412/html5/0.jpg"/>
    <right url="pano_412/html5/1.jpg"/>
    <back  url="pano_412/html5/2.jpg"/>
    <left  url="pano_412/html5/3.jpg"/>
    <up    url="pano_412/html5/4.jpg"/>
    <down  url="pano_412/html5/5.jpg"/>
  </image>
  
      <image type="CUBE" devices="tablet">
        <front url="pano_412/tablet/0.jpg"/>
        <right url="pano_412/tablet/1.jpg"/>
        <back  url="pano_412/tablet/2.jpg"/>
        <left  url="pano_412/tablet/3.jpg"/>
        <up    url="pano_412/tablet/4.jpg"/>
        <down  url="pano_412/tablet/5.jpg"/>
      </image>
      <image type="CUBE" devices="mobile">
        <front url="pano_412/mobile/0.jpg"/>
        <right url="pano_412/mobile/1.jpg"/>
        <back  url="pano_412/mobile/2.jpg"/>
        <left  url="pano_412/mobile/3.jpg"/>
        <up    url="pano_412/mobile/4.jpg"/>
        <down  url="pano_412/mobile/5.jpg"/>
      </image>


  <!-- **** 1 Point Spots **** -->



  <hotspot name="spotpoint438"
           ath="34.359119" atv="12.065558"
           style="IconLoadpanorama"
           tag="point"
           descriptionid=""
           onclick="onclickspotpoint438"
           tooltip="spotpoint438_tooltip"
           />
  <hotspot name="spotpoint438" devices="flash" zorder="3"/>
  <hotspot name="spotpoint438" devices="html5" zorder="3" zorder2="1"/>
  <action name="onclickspotpoint438">
  
        mainloadscene(pano409);lookat(get(panoview.h), get(panoview.v), get(panoview.fov));


  </action>



  <action name="hidepanopointspots">
    set(hotspot[spotpoint438].visible, false);
  </action>
  <action name="showpanopointspots">
    set(hotspot[spotpoint438].visible, true);
  </action>
  <events name="pano412stopanimatedspots" onremovepano="stopspotanimation(spotpoint438);" />


  <action name="showpanospotsaction">
    resumeTourSoundsActions(true,false,false,false,true);
    if (tour_displayspots,
    showpanopointspots();
    );
  </action>
  <action name="hidepanospotsaction">
    pauseTourSoundsActions(true,false,false,false,true);
    hidepanopointspots();
  </action>


  <action name="setzorder2onstandardspots">
    if (device.html5,
      ifnot (device.desktop,


        tween(hotspot[spotpoint438].zorder2, %1);

      );
    );
  </action>


</scene>


  <krpano nofullspherepanoavailable="true" />


  <!-- Awake HTML5 plugins -->
  <events name="eventKrpanoLoadedEvts" onxmlcomplete="eventKrpanoLoadedAction();" keep="true" />
  <action name="eventKrpanoLoadedAction">
    
    set(events[eventKrpanoLoadedEvts].name, null);
    js(eventKrpanoLoaded());
  </action>

</krpano>

